setup.cfg
setup.py
continuation/__init__.py
continuation.egg-info/PKG-INFO
continuation.egg-info/SOURCES.txt
continuation.egg-info/dependency_links.txt
continuation.egg-info/top_level.txt