Metadata-Version: 1.0
Name: continuation
Version: 0.1
Summary: Handling continuations in Python
Home-page: https://github.com/baruchel/continuation
Author: Thomas Baruchel
Author-email: baruchel@gmx.com
License: MIT
Platform: UNKNOWN
